queue_sqlite/__init__.py
queue_sqlite/py.typed
queue_sqlite/constant/__init__.py
queue_sqlite/constant/message_priority.py
queue_sqlite/constant/message_status.py
queue_sqlite/constant/message_type.py
queue_sqlite/cycle/__init__.py
queue_sqlite/cycle/async_task_cycle.py
queue_sqlite/cycle/task_cycle.py
queue_sqlite/model/__init__.py
queue_sqlite/model/message_item.py
queue_sqlite/model/scheduler_config.py
queue_sqlite/mounter/__init__.py
queue_sqlite/mounter/listen_mounter.py
queue_sqlite/mounter/task_mounter.py
queue_sqlite/queue_operation/__init__.py
queue_sqlite/queue_operation/listen_operation.py
queue_sqlite/scheduler/__init__.py
queue_sqlite/scheduler/cleanup_scheduler.py
queue_sqlite/scheduler/_async/__init__.py
queue_sqlite/scheduler/_async/async_listen_data_scheduler.py
queue_sqlite/scheduler/_async/async_receive_scheduler.py
queue_sqlite/scheduler/_async/async_task_scheduler.py
queue_sqlite/scheduler/base/__init__.py
queue_sqlite/scheduler/base/base_scheduler.py
queue_sqlite/scheduler/qt/__init__.py
queue_sqlite/scheduler/qt/callback_task.py
queue_sqlite/scheduler/qt/listen_scheduler.py
queue_sqlite/scheduler/qt/listen_task.py
queue_sqlite/scheduler/qt/receive_scheduler.py
queue_sqlite/scheduler/qt/task_executor.py
queue_sqlite/scheduler/qt/task_scheduler.py
queue_sqlite/scheduler/standard/__init__.py
queue_sqlite/scheduler/standard/listen_data_scheduler.py
queue_sqlite/scheduler/standard/receive_scheduler.py
queue_sqlite/scheduler/standard/task_scheduler.py
queue_sqlite-0.2.3.dist-info/METADATA
queue_sqlite-0.2.3.dist-info/WHEEL
queue_sqlite-0.2.3.dist-info/licenses/LICENSE
queue_sqlite-0.2.3.dist-info/RECORD
