Metadata-Version: 2.4
Name: queue-sqlite
Version: 0.2.3
Summary: A high-performance, SQLite-based distributed task queue system with Rust-backed core operations. Supports task mounting, message listening, priority handling, retry mechanisms, and automatic cleanup of expired messages. Ideal for building reliable, scalable background task processing systems.
Author-email: chakcy <947105045@qq.com>
License-File: LICENSE
Classifier: Development Status :: 4 - Beta
Classifier: Intended Audience :: Developers
Classifier: License :: OSI Approved :: MIT License
Classifier: Operating System :: Microsoft :: Windows
Classifier: Operating System :: POSIX :: Linux
Classifier: Programming Language :: Python :: 3
Classifier: Topic :: System :: Distributed Computing
Classifier: Typing :: Typed
Requires-Python: >=3.11
Requires-Dist: queue-sqlite-core>=0.2.0
Provides-Extra: pyqt5
Requires-Dist: pyqt5; extra == 'pyqt5'
Requires-Dist: qtpy; extra == 'pyqt5'
Provides-Extra: pyqt6
Requires-Dist: pyqt6; extra == 'pyqt6'
Requires-Dist: qtpy; extra == 'pyqt6'
Provides-Extra: pyside6
Requires-Dist: pyside6; extra == 'pyside6'
Requires-Dist: qtpy; extra == 'pyside6'
